[
  {
    "id": 0,
    "parentId": -1,
    "ins_id": "",
    "tag": "div",
    "mini_method_uuid": -1,
    "data": {
      "$style": {
        "width": "100%",
        "height": "100%",
        "overflow": "auto"
      }
    }
  },
  {
    "id": 1,
    "parentId": 0,
    "ins_id": "",
    "tag": "van-goods-action-button",
    "mini_method_uuid": -1,
    "data": {
      "$style": {},
      "type": "default",
      "disabled": false,
      "loading": false,
      "replace": false,
      "$exports": [
        {
          "attrKey": "replace",
          "alias": "是否在跳转时替换当前页面历史",
          "sortIdx": -1
        },
        {
          "attrKey": "to",
          "alias": "点击后跳转的目标路由对象，同 vue-router 的  to 属性",
          "sortIdx": -1
        },
        {
          "attrKey": "url",
          "alias": "点击后跳转的链接地址",
          "sortIdx": -1
        },
        {
          "attrKey": "loading",
          "alias": "是否显示为加载状态",
          "sortIdx": -1
        },
        {
          "attrKey": "disabled",
          "alias": "是否禁用按钮",
          "sortIdx": -1
        },
        {
          "attrKey": "icon",
          "alias": "左侧 图标名称 或图片链接",
          "sortIdx": -1
        },
        {
          "attrKey": "color",
          "alias": "按钮颜色，支持传入 linear-gradient 渐变色",
          "sortIdx": -1
        },
        {
          "attrKey": "type",
          "alias": "按钮类型，可选值为  primary info warning danger",
          "sortIdx": -1
        },
        {
          "attrKey": "text",
          "alias": "goodsactionbutton 商品图标导航 按钮文字",
          "sortIdx": -1
        },
        {
          "attrKey": "v-if",
          "alias": "v-if指令",
          "sortIdx": -1
        },
        {
          "attrKey": "v-show",
          "alias": "v-show指令",
          "sortIdx": -1
        },
        {
          "attrKey": "v-model",
          "alias": "v-model指令",
          "sortIdx": -1
        }
      ],
      "$exportState": true
    }
  }
]